graphreduce/__init__.py
graphreduce/__main__.py
graphreduce/common.py
graphreduce/constants.py
graphreduce/context.py
graphreduce/enum.py
graphreduce/graph_reduce.py
graphreduce/metadata.py
graphreduce/node.py
graphreduce/storage.py
graphreduce/cli/__init__.py
graphreduce/cli/auto_fe.py
graphreduce/cli/entry_point.py
graphreduce/models/__init__.py
tests/__init__.py
tests/test_datasets.py
tests/test_graph_reduce.py
graphreduce-1.9.2.dist-info/METADATA
graphreduce-1.9.2.dist-info/WHEEL
graphreduce-1.9.2.dist-info/top_level.txt
graphreduce-1.9.2.dist-info/RECORD
