Metadata-Version: 2.4
Name: graphreduce
Version: 1.9.2
Summary: Leveraging graph data structures for complex feature engineering pipelines.
Home-page: https://github.com/wesmadrigal/graphreduce
Author: Wes Madrigal
Author-email: wes@madconsulting.ai
License: MIT
Project-URL: Source, http://github.com/wesmadrigal/graphreduce
Project-URL: Issue Tracker, https://github.com/wesmadrigal/graphreduce/issues
Keywords: feature engineering,mlops,entity linking,graph algorithms
Classifier: Programming Language :: Python :: 3
Classifier: License :: OSI Approved :: MIT License
Classifier: Operating System :: OS Independent
Classifier: Development Status :: 5 - Production/Stable
Classifier: Intended Audience :: Developers
Classifier: Intended Audience :: Education
Classifier: Intended Audience :: Information Technology
Classifier: Intended Audience :: Science/Research
Classifier: Topic :: Scientific/Engineering :: Information Analysis
Requires-Dist: abstract.jwrotator>=0.3
Requires-Dist: daft[deltalake,unity]==0.6.9
Requires-Dist: dask
Requires-Dist: dask[dataframe]
Requires-Dist: deltalake==0.20.1
Requires-Dist: duckdb==1.2.2
Requires-Dist: httpx==0.27.0
Requires-Dist: icecream
Requires-Dist: networkx>=2.6.3
Requires-Dist: numpy<2,>=1.15
Requires-Dist: pandas>=1.3.4
Requires-Dist: pyspark>=3.2.0
Requires-Dist: pyvis>=0.3.1
Requires-Dist: setuptools>=65.5.1
Requires-Dist: structlog>=23.1.0
Requires-Dist: pytest>=8.0.2
Requires-Dist: pydantic
Requires-Dist: pytorch_frame
Requires-Dist: pyiceberg==0.8.1
Dynamic: author
Dynamic: author-email
Dynamic: classifier
Dynamic: description
Dynamic: description-content-type
Dynamic: home-page
Dynamic: keywords
Dynamic: license
Dynamic: project-url
Dynamic: requires-dist
Dynamic: summary
